MANIFEST.in
README.md
setup.py
robotpt_common_utils/__init__.py
robotpt_common_utils/dates.py
robotpt_common_utils/lists.py
robotpt_common_utils/math_tools.py
robotpt_common_utils/pandas_lib.py
robotpt_common_utils/strings.py
robotpt_common_utils/system.py
robotpt_common_utils/user_input.py
robotpt_common_utils.egg-info/PKG-INFO
robotpt_common_utils.egg-info/SOURCES.txt
robotpt_common_utils.egg-info/dependency_links.txt
robotpt_common_utils.egg-info/requires.txt
robotpt_common_utils.egg-info/top_level.txt